{
  "@microsoft/generator-sharepoint": {
    "plusBeta": false,
    "isCreatingSolution": true,
    "nodeVersion": "20.16.0",
    "sdksVersions": {
      "@microsoft/microsoft-graph-client": "3.0.2",
      "@microsoft/teams-js": "2.12.0"
    },
    "version": "1.19.0",
    "libraryName": "readers-jvap",
    "libraryId": "3262121c-1848-4fb2-94e7-d845f75aa837",
    "environment": "spo",
    "packageManager": "npm",
    "solutionName": "readers-jvap",
    "solutionShortDescription": "readers-jvap description",
    "skipFeatureDeployment": true,
    "isDomainIsolated": false,
    "componentType": "webpart"
  }
}
